holger/LICENSE
holger/README.md
holger/__init__.py
holger/status.py
holger/.git/COMMIT_EDITMSG
holger/.git/FETCH_HEAD
holger/.git/HEAD
holger/.git/ORIG_HEAD
holger/.git/config
holger/.git/description
holger/.git/index
holger/.git/hooks/applypatch-msg.sample
holger/.git/hooks/commit-msg.sample
holger/.git/hooks/fsmonitor-watchman.sample
holger/.git/hooks/post-update.sample
holger/.git/hooks/pre-applypatch.sample
holger/.git/hooks/pre-commit.sample
holger/.git/hooks/pre-push.sample
holger/.git/hooks/pre-rebase.sample
holger/.git/hooks/pre-receive.sample
holger/.git/hooks/prepare-commit-msg.sample
holger/.git/hooks/update.sample
holger/.git/info/exclude
holger/.git/logs/HEAD
holger/.git/logs/refs/stash
holger/.git/logs/refs/heads/auth
holger/.git/logs/refs/heads/master
holger/.git/logs/refs/remotes/gitlab/auth
holger/.git/logs/refs/remotes/gitlab/master
holger/.git/objects/01/2fbe31d5f051755c80bdc0d1878aa2a6c7c908
holger/.git/objects/04/8b4731e572b7feba8264553c4e02102a1fca84
holger/.git/objects/04/998ad398452a10dff84c4671201074cb92727b
holger/.git/objects/05/1096a5aeae9ec42c8c0d4fe4176d595bb0f821
holger/.git/objects/06/a0230e940735f25ea490291ba2ed85da58153f
holger/.git/objects/0d/f3010c6795a817d9d4911f0bd7e1b5dc222e91
holger/.git/objects/0e/23bd2ee5a3c75110d140e4e2127d10c3480ee5
holger/.git/objects/14/97c7f75aa45ef95f6ae3de65e5fc4bf382bb5f
holger/.git/objects/14/a6e4da4e35da157695462c75f3e67091c8bbfc
holger/.git/objects/15/3696305277dff1b6b265a62f1d9c198d16415b
holger/.git/objects/18/7fb00a6ce84c4691bce9ed2bd57b281a0a790a
holger/.git/objects/19/e5d803d636e25442de9fe34bf187f5b4df9e86
holger/.git/objects/21/0e9dd565a8c479e197239d100a83c7a304043a
holger/.git/objects/23/aa1ed8e5f69daa6b5165de49e207952074cc9f
holger/.git/objects/26/6735805359b33103eb8053109ce25bb96f5ed8
holger/.git/objects/2e/377205c058f0efcb133953fdd5540826f5065a
holger/.git/objects/30/9ddc4aeb6365a020b4f1f4be7e1b7edeed3cb6
holger/.git/objects/31/9308dc87cd5b6287a17572b960e34fffa3129a
holger_utils-0.7.12.dist-info/METADATA
holger_utils-0.7.12.dist-info/WHEEL
holger_utils-0.7.12.dist-info/top_level.txt
holger_utils-0.7.12.dist-info/RECORD
