Metadata-Version: 2.1
Name: holger-utils
Version: 0.7.12
Summary: utils for developing web application
Home-page: https://gitlab.com/football-fantasy/holger-utils
Author: Mohammad Hosein Shamsaei
Author-email: holgerco.dev@gmail.com
License: UNKNOWN
Platform: UNKNOWN
Classifier: Environment :: Web Environment
Classifier: Programming Language :: Python :: 3
Classifier: License :: OSI Approved :: MIT License
Classifier: Operating System :: OS Independent
Classifier: Framework :: Django
Classifier: Intended Audience :: Developers
Classifier: Topic :: Internet :: WWW/HTTP
Requires-Python: >=3.6
Requires-Dist: requests
Requires-Dist: djangorestframework
Requires-Dist: elasticsearch[async]
Requires-Dist: celery
Requires-Dist: sentry-sdk
Requires-Dist: python-dateutil
Requires-Dist: firebase-admin
Requires-Dist: google-api-python-client
Requires-Dist: python-jose
Requires-Dist: pycryptodome
Requires-Dist: django-nose
Requires-Dist: djangorestframework-simplejwt
Requires-Dist: jdatetime
Requires-Dist: django-phonenumber-field
Requires-Dist: phonenumbers
Requires-Dist: kavenegar
Requires-Dist: django-cryptography
Requires-Dist: pyJWT
Requires-Dist: Babel
